{
  "hash": "8b8e8cc1",
  "configHash": "92b71aca",
  "lockfileHash": "4b5f9d06",
  "browserHash": "adbbf3e4",
  "optimized": {
    "framer-motion": {
      "src": "../../node_modules/framer-motion/dist/es/index.mjs",
      "file": "framer-motion.js",
      "fileHash": "27d30168",
      "needsInterop": false
    },
    "lucide-react": {
      "src": "../../node_modules/lucide-react/dist/esm/lucide-react.js",
      "file": "lucide-react.js",
      "fileHash": "805e2b2d",
      "needsInterop": false
    },
    "react": {
      "src": "../../node_modules/react/index.js",
      "file": "react.js",
      "fileHash": "ade49ce1",
      "needsInterop": true
    },
    "react-dom/client": {
      "src": "../../node_modules/react-dom/client.js",
      "file": "react-dom_client.js",
      "fileHash": "44493c6a",
      "needsInterop": true
    }
  },
  "chunks": {
    "chunk-WYYPSHNY": {
      "file": "chunk-WYYPSHNY.js"
    }
  }
}